llm7token/__init__.py
llm7token-2025.12.51256.dist-info/licenses/LICENSE
llm7token-2025.12.51256.dist-info/METADATA
llm7token-2025.12.51256.dist-info/WHEEL
llm7token-2025.12.51256.dist-info/top_level.txt
llm7token-2025.12.51256.dist-info/RECORD
