Metadata-Version: 2.4
Name: llm7token
Version: 2025.12.51256
Summary: Utilities for validating and reporting LLM7 API tokens.
Home-page: https://github.com/chigwell/llm7token
Author: Eugene Evstafev
Author-email: support@llm7.io
License: MIT
Classifier: License :: OSI Approved :: MIT License
Classifier: Development Status :: 3 - Alpha
Classifier: Intended Audience :: Developers
Classifier: Programming Language :: Python :: 3
Classifier: Operating System :: OS Independent
Requires-Python: >=3.6
License-File: LICENSE
Requires-Dist: requests==2.32.3
Requires-Dist: cryptography==45.0.3
Dynamic: author
Dynamic: author-email
Dynamic: classifier
Dynamic: description
Dynamic: description-content-type
Dynamic: home-page
Dynamic: license
Dynamic: license-file
Dynamic: requires-dist
Dynamic: requires-python
Dynamic: summary
